umedsmsclient/__init__.py
umedsmsclient/exceptions.py
umedsmsclient/fire_text_api_client.py
umedsmsclient-1.0.0.dist-info/LICENSE
umedsmsclient-1.0.0.dist-info/METADATA
umedsmsclient-1.0.0.dist-info/WHEEL
umedsmsclient-1.0.0.dist-info/top_level.txt
umedsmsclient-1.0.0.dist-info/RECORD
