Metadata-Version: 2.1
Name: umedsmsclient
Version: 1.0.0
Summary: A Python client library for sending and scheduling sms messages via Fire Text Sms API
Home-page: https://github.com/hasithaprageeth/umed-sms-client
Author: Hasitha Widanagamachchi
Author-email: haztha@gmail.com
Classifier: Development Status :: 3 - Alpha
Classifier: Intended Audience :: Developers
Classifier: License :: OSI Approved :: MIT License
Classifier: Programming Language :: Python :: 3.7
Classifier: Programming Language :: Python :: 3.8
Classifier: Programming Language :: Python :: 3.9
License-File: LICENSE
Requires-Dist: requests
